{
    "run_id": "run_20251203_114000",
    "model_name": "XGBoost",
    "params": {
        "n_estimators": 100,
        "learning_rate": 0.1,
        "max_depth": 6
    },
    "start_time": "2025-12-03T11:40:00.350650",
    "status": "completed",
    "data_info": {
        "n_samples": 408,
        "n_features": 36,
        "feature_names": [
            "year",
            "month",
            "day",
            "day_of_week",
            "day_of_year",
            "week_of_year",
            "quarter",
            "is_weekend",
            "is_month_start",
            "is_month_end",
            "is_quarter_start",
            "is_quarter_end",
            "month_sin",
            "month_cos",
            "day_of_week_sin",
            "day_of_week_cos",
            "views_lag_1",
            "views_lag_7",
            "views_lag_14",
            "views_lag_30",
            "views_rolling_mean_7",
            "views_rolling_std_7",
            "views_rolling_min_7",
            "views_rolling_max_7",
            "views_rolling_mean_14",
            "views_rolling_std_14",
            "views_rolling_min_14",
            "views_rolling_max_14",
            "views_rolling_mean_30",
            "views_rolling_std_30",
            "views_rolling_min_30",
            "views_rolling_max_30",
            "category_lifestyle",
            "category_news",
            "category_tech",
            "category_tutorial"
        ]
    },
    "end_time": "2025-12-03T11:40:00.790284",
    "training_time": 0.422642,
    "metrics": {
        "MSE": 16513.26953125,
        "RMSE": 128.50396698643198,
        "MAE": 100.50106048583984,
        "MAPE": 8.713633567094803,
        "R\u00b2": 0.36864447593688965,
        "SMAPE": 8.929245689085828,
        "Bias": -42.78564094094669
    }
}